setup.py
examples/__init__.py
examples/simple.py
strowger/__init__.py
strowger/_version.py
strowger/switch.py
strowger.egg-info/PKG-INFO
strowger.egg-info/SOURCES.txt
strowger.egg-info/dependency_links.txt
strowger.egg-info/requires.txt
strowger.egg-info/top_level.txt
tests/__init__.py
tests/test_map.py
tests/test_switch.py