Metadata-Version: 1.0
Name: strowger
Version: 0.1.3
Summary: Lightweight Twilio SMS application framework
Home-page: https://github.com/skimbrel/strowger
Author: Sam Kimbrel
Author-email: samkimbrel@gmail.com
License: UNKNOWN
Keywords: strowger,twilio,twiml,sms
Platform: UNKNOWN
Classifier: Development Status :: 4 - Beta
Classifier: Intended Audience :: Developers
Classifier: License :: OSI Approved :: BSD License
Classifier: Operating System :: OS Independent
Classifier: Programming Language :: Python :: 2.6
Classifier: Programming Language :: Python :: 2.7
Classifier: Programming Language :: Python :: 3.2
Classifier: Programming Language :: Python :: 3.3
Classifier: Topic :: Software Development :: Libraries :: Python Modules
Classifier: Topic :: Communications :: Telephony
Classifier: Topic :: Internet :: WWW/HTTP :: WSGI :: Application
